foundry_dev_tools_transforms-2.1.22.dist-info/METADATA
foundry_dev_tools_transforms-2.1.22.dist-info/WHEEL
foundry_dev_tools_transforms-2.1.22.dist-info/entry_points.txt
transforms/__about__.py
transforms/__init__.py
transforms/api/__init__.py
transforms/api/_configure.py
transforms/api/_dataset.py
transforms/api/_decorators.py
transforms/api/_transform.py
transforms/errors.py
transforms/py.typed
foundry_dev_tools_transforms-2.1.22.dist-info/RECORD
