Metadata-Version: 2.1
Name: foundry-dev-tools-transforms
Version: 2.1.22
Summary: Seamlessly run your Palantir Foundry Repository transforms code on your local machine.
Author-Email: Nicolas Renkamp <nicolas.renkamp@merckgroup.com>, Jonas Wunderlich <jonas.wunderlich@merckgroup.com>
License: Apache-2.0
Classifier: Development Status :: 5 - Production/Stable
Classifier: Programming Language :: Python
Classifier: License :: OSI Approved :: Apache Software License
Classifier: Programming Language :: Python :: 3 :: Only
Classifier: Programming Language :: Python :: 3.10
Classifier: Programming Language :: Python :: 3.11
Classifier: Intended Audience :: Developers
Classifier: Operating System :: POSIX :: Linux
Classifier: Operating System :: MacOS
Classifier: Operating System :: Microsoft :: Windows
Classifier: Topic :: Scientific/Engineering :: Information Analysis
Project-URL: Homepage, https://emdgroup.github.io/foundry-dev-tools
Project-URL: Documentation, https://emdgroup.github.io/foundry-dev-tools
Project-URL: Source, https://github.com/emdgroup/foundry-dev-tools
Project-URL: Tracker, https://github.com/emdgroup/foundry-dev-tools/issues
Project-URL: Changelog, https://emdgroup.github.io/foundry-dev-tools/changelog.html
Requires-Python: >=3.10
Requires-Dist: foundry-dev-tools
Requires-Dist: typing_extensions; python_version < "3.11"
Requires-Dist: pyspark>=3.0.0
Requires-Dist: numpy<2
Requires-Dist: fs
